{
	"package": {
		"name": "@aleworm/svelte-skeleton-loader",
		"scope": "aleworm",
		"version": "0.0.3",
		"description": "Everything you need to build a Svelte project, powered by [`create-svelte`](https://github.com/sveltejs/kit/tree/master/packages/create-svelte).",
		"date": "2022-11-07T03:17:21.547Z",
		"links": {
			"npm": "https://www.npmjs.com/package/%40aleworm%2Fsvelte-skeleton-loader"
		},
		"publisher": {
			"username": "aleworm",
			"email": "alexander.wormbs@gmail.com"
		},
		"maintainers": [
			{
				"username": "aleworm",
				"email": "alexander.wormbs@gmail.com"
			}
		]
	},
	"flags": {
		"unstable": true
	},
	"score": {
		"final": 0.22658217060425428,
		"detail": {
			"quality": 0.35118877309626423,
			"popularity": 0.013117576919555746,
			"maintenance": 0.33324110501008714
		}
	},
	"searchScore": 5.9278673e-8
}