{
	"package": {
		"name": "@beeanco/svelte-docs",
		"scope": "beeanco",
		"version": "0.2.0",
		"description": "Generate documentation from svelte components",
		"date": "2021-10-09T13:57:44.944Z",
		"links": {
			"npm": "https://www.npmjs.com/package/%40beeanco%2Fsvelte-docs",
			"homepage": "https://lukashechenberger.github.io/beeanco-opensource/docs/svelte-docs/"
		},
		"author": {
			"name": "Lukas Hechenberger",
			"email": "npm@ls-age.com",
			"username": "lhechenberger"
		},
		"publisher": {
			"username": "lhechenberger",
			"email": "npm@ls-age.com"
		},
		"maintainers": [
			{
				"username": "lhechenberger",
				"email": "npm@ls-age.com"
			}
		]
	},
	"flags": {
		"unstable": true
	},
	"score": {
		"final": 0.19060881146093797,
		"detail": {
			"quality": 0.5088299857230272,
			"popularity": 0.0014518238078102884,
			"maintenance": 0.10700479260370344
		}
	},
	"searchScore": 7.0890547e-9
}