{
	"package": {
		"name": "@devappd/svelte-resize-observer",
		"scope": "devappd",
		"version": "1.1.0",
		"description": "Element resize observer to Svelte using @juggle/resize-observer",
		"keywords": [
			"svelte",
			"resize",
			"observer"
		],
		"date": "2021-01-15T08:43:24.271Z",
		"links": {
			"npm": "https://www.npmjs.com/package/%40devappd%2Fsvelte-resize-observer",
			"homepage": "https://svelte-resize-observer.netlify.com/",
			"repository": "https://github.com/andrelmlins/svelte-resize-observer",
			"bugs": "https://github.com/andrelmlins/svelte-resize-observer/issues"
		},
		"author": {
			"name": "André Lins",
			"email": "andrelucas01@hotmail.com",
			"url": "https://andrelmlins.github.io/"
		},
		"publisher": {
			"username": "devappd",
			"email": "devappd@outlook.com"
		},
		"maintainers": [
			{
				"username": "devappd",
				"email": "devappd@outlook.com"
			}
		]
	},
	"score": {
		"final": 0.21814998112544964,
		"detail": {
			"quality": 0.621149076937051,
			"popularity": 0.001130468303792204,
			"maintenance": 0.089741697537163
		}
	},
	"searchScore": 5.140219e-8
}