{
	"package": {
		"name": "@direktspeed/baseurl",
		"scope": "direktspeed",
		"version": "0.1.1",
		"description": "A Static Replaceable Adjustable Modifiy able baseUrl for your Applications",
		"keywords": [
			"baseurl",
			"import",
			"helper",
			"cross",
			"platform",
			"electron",
			"svelte",
			"react",
			"vue"
		],
		"date": "2023-01-07T03:58:31.641Z",
		"links": {
			"npm": "https://www.npmjs.com/package/%40direktspeed%2Fbaseurl"
		},
		"author": {
			"name": "Frank Lemanschik",
			"email": "frank@dspeed.eu",
			"username": "frank-dspeed"
		},
		"publisher": {
			"username": "frank-dspeed",
			"email": "frank@dspeed.eu"
		},
		"maintainers": [
			{
				"username": "direktspeed-backup",
				"email": "direktspeed@gmail.com"
			},
			{
				"username": "frank-dspeed",
				"email": "frank@dspeed.eu"
			}
		]
	},
	"flags": {
		"unstable": true
	},
	"score": {
		"final": 0.23845590090530977,
		"detail": {
			"quality": 0.40415024875407274,
			"popularity": 0.002981829382408996,
			"maintenance": 0.33190624570069943
		}
	},
	"searchScore": 4.1715484e-8
}