{
	"package": {
		"name": "@edde746/svelte-apexcharts",
		"scope": "edde746",
		"version": "1.0.11",
		"description": "Everything you need to build a Svelte project, powered by [`create-svelte`](https://github.com/sveltejs/kit/tree/master/packages/create-svelte).",
		"date": "2022-09-28T22:01:12.911Z",
		"links": {
			"npm": "https://www.npmjs.com/package/%40edde746%2Fsvelte-apexcharts"
		},
		"publisher": {
			"username": "edde746",
			"email": "edvard.wikhall@gmail.com"
		},
		"maintainers": [
			{
				"username": "edde746",
				"email": "edvard.wikhall@gmail.com"
			}
		]
	},
	"score": {
		"final": 0.2482564889433188,
		"detail": {
			"quality": 0.4160617952064585,
			"popularity": 0.01957431937479419,
			"maintenance": 0.33310553885772376
		}
	},
	"searchScore": 2.4170305e-7
}