{
	"package": {
		"name": "@ethercorps/sveltekit-redis-session",
		"scope": "ethercorps",
		"version": "0.2.0",
		"description": "<a name=\"readme-top\"></a> [![Contributors][contributors-shield]][contributors-url] [![Forks][forks-shield]][forks-url] [![Stargazers][stars-shield]][stars-url] [![Issues][issues-shield]][issues-url] [![MIT License][license-shield]][license-url] [![LinkedI",
		"keywords": [
			"sveltekit-redis-session",
			"sveltekit redis session manager",
			"sveltekit redis",
			"sveltekit session manager",
			"sveltekit session",
			"@ethercorps/sveltekit-redis-session"
		],
		"date": "2023-03-10T06:34:40.487Z",
		"links": {
			"npm": "https://www.npmjs.com/package/%40ethercorps%2Fsveltekit-redis-session",
			"homepage": "https://github.com/etherCorps/SK-Redis-SessionManager#readme",
			"repository": "https://github.com/etherCorps/SK-Redis-SessionManager",
			"bugs": "https://github.com/etherCorps/SK-Redis-SessionManager/issues"
		},
		"publisher": {
			"username": "ethercorps.io",
			"email": "shivam@theether.in"
		},
		"maintainers": [
			{
				"username": "ethercorps.io",
				"email": "shivam@theether.in"
			}
		]
	},
	"flags": {
		"unstable": true
	},
	"score": {
		"final": 0.25333592200642047,
		"detail": {
			"quality": 0.44931076050864066,
			"popularity": 0.006787165310238529,
			"maintenance": 0.33190624570069943
		}
	},
	"searchScore": 1.2915704e-7
}