{
	"package": {
		"name": "@htmlbricks/hb-vertical-img-txt-archive",
		"scope": "htmlbricks",
		"version": "0.19.31",
		"description": "Svelte-Bootstrap vertical-img-txt-archive",
		"keywords": [
			"svelte",
			"svelte-webcomponents",
			"webcomponents"
		],
		"date": "2023-02-28T18:24:14.278Z",
		"links": {
			"npm": "https://www.npmjs.com/package/%40htmlbricks%2Fhb-vertical-img-txt-archive"
		},
		"author": {
			"name": "Dario Caruso",
			"email": "dev@dariocaruso.info",
			"url": "https://dariocaruso.info"
		},
		"publisher": {
			"username": "dariocaruso",
			"email": "darioyzf@gmail.com"
		},
		"maintainers": [
			{
				"username": "dariocaruso",
				"email": "darioyzf@gmail.com"
			}
		]
	},
	"flags": {
		"unstable": true
	},
	"score": {
		"final": 0.21952381373961685,
		"detail": {
			"quality": 0.3189153586726388,
			"popularity": 0.020521541346167314,
			"maintenance": 0.3333333333333333
		}
	},
	"searchScore": 3.1440496e-8
}