{
	"package": {
		"name": "@htmlbricks/hb-searchbar",
		"scope": "htmlbricks",
		"version": "0.19.31",
		"description": "Svelte Search Bar WebComponent",
		"keywords": [
			"svelte",
			"svelte-webcomponents",
			"webcomponents",
			"html5-webcomponents"
		],
		"date": "2023-02-28T18:24:11.655Z",
		"links": {
			"npm": "https://www.npmjs.com/package/%40htmlbricks%2Fhb-searchbar"
		},
		"author": {
			"name": "Dario Caruso",
			"email": "dev@dariocaruso.info",
			"url": "https://dariocaruso.info"
		},
		"publisher": {
			"username": "dariocaruso",
			"email": "darioyzf@gmail.com"
		},
		"maintainers": [
			{
				"username": "dariocaruso",
				"email": "darioyzf@gmail.com"
			}
		]
	},
	"flags": {
		"unstable": true
	},
	"score": {
		"final": 0.23073349072846044,
		"detail": {
			"quality": 0.3565995147262083,
			"popularity": 0.02024848469694661,
			"maintenance": 0.3333333333333333
		}
	},
	"searchScore": 5.8985222e-8
}