{
	"package": {
		"name": "@minna-ui/svelte-preprocess-markup",
		"scope": "minna-ui",
		"version": "0.16.0",
		"description": "Svelte markup preprocessor for use in minna-ui projects.",
		"keywords": [
			"html",
			"minify-html",
			"minna-ui",
			"svelte",
			"wearegenki"
		],
		"date": "2018-10-21T03:34:59.228Z",
		"links": {
			"npm": "https://www.npmjs.com/package/%40minna-ui%2Fsvelte-preprocess-markup"
		},
		"author": {
			"name": "Max Milton",
			"email": "max@wearegenki.com",
			"username": "maxmilton"
		},
		"publisher": {
			"username": "maxmilton",
			"email": "max@wearegenki.com"
		},
		"maintainers": [
			{
				"username": "maxmilton",
				"email": "max@wearegenki.com"
			}
		]
	},
	"flags": {
		"unstable": true
	},
	"score": {
		"final": 0.24914983435080068,
		"detail": {
			"quality": 0.702872582756977,
			"popularity": 0.019652758244858667,
			"maintenance": 0.089741697537163
		}
	},
	"searchScore": 3.40126e-7
}