{
	"package": {
		"name": "@minna-ui/navbar",
		"scope": "minna-ui",
		"version": "0.36.0",
		"description": "😸 A fast, friendly, and fun web UI kit for everyone.",
		"keywords": [
			"component",
			"design-system",
			"minna-ui",
			"postcss",
			"svelte",
			"svelte-components",
			"ui-components",
			"wearegenki",
			"web-components"
		],
		"date": "2020-03-24T19:40:16.110Z",
		"links": {
			"npm": "https://www.npmjs.com/package/%40minna-ui%2Fnavbar",
			"homepage": "https://wearegenki.github.io/minna-ui"
		},
		"author": {
			"name": "Max Milton",
			"email": "max@wearegenki.com",
			"username": "maxmilton"
		},
		"publisher": {
			"username": "maxmilton",
			"email": "max@wearegenki.com"
		},
		"maintainers": [
			{
				"username": "maxmilton",
				"email": "max@wearegenki.com"
			}
		]
	},
	"flags": {
		"unstable": true
	},
	"score": {
		"final": 0.25199429091040315,
		"detail": {
			"quality": 0.7041766562301651,
			"popularity": 0.026661999723847366,
			"maintenance": 0.089741697537163
		}
	},
	"searchScore": 1.6948381e-7
}