{
	"package": {
		"name": "@novacbn/svelte-pipeline",
		"scope": "novacbn",
		"version": "0.3.1",
		"description": "Provides custom Javascript evaluation contexts and the Svelte Compiler as Svelte Stores, for REPLs, IDEs, etc.",
		"keywords": [
			"compiler",
			"repl",
			"svelte",
			"svelte-components",
			"svelte-stores"
		],
		"date": "2022-03-07T09:33:56.866Z",
		"links": {
			"npm": "https://www.npmjs.com/package/%40novacbn%2Fsvelte-pipeline"
		},
		"author": {
			"name": "novacbn"
		},
		"publisher": {
			"username": "novacbn",
			"email": "novacbn@gmail.com"
		},
		"maintainers": [
			{
				"username": "novacbn",
				"email": "novacbn@gmail.com"
			}
		]
	},
	"flags": {
		"unstable": true
	},
	"score": {
		"final": 0.2024868563464854,
		"detail": {
			"quality": 0.3941765747802062,
			"popularity": 0.018870180544704532,
			"maintenance": 0.22179805920507703
		}
	},
	"searchScore": 2.1785302e-8
}