{
	"package": {
		"name": "@oliverjam/eleventy-plugin-svelte",
		"scope": "oliverjam",
		"version": "2.0.1",
		"description": "Use Svelte components as Eleventy templates",
		"keywords": [
			"eleventy",
			"eleventy-plugin",
			"svelte"
		],
		"date": "2020-08-15T18:34:33.677Z",
		"links": {
			"npm": "https://www.npmjs.com/package/%40oliverjam%2Feleventy-plugin-svelte",
			"homepage": "https://github.com/oliverjam/eleventy-plugin-svelte#readme",
			"repository": "https://github.com/oliverjam/eleventy-plugin-svelte",
			"bugs": "https://github.com/oliverjam/eleventy-plugin-svelte/issues"
		},
		"author": {
			"name": "Oliver Phillips",
			"email": "hello@oliverjam.es",
			"url": "https://oliverjam.es"
		},
		"publisher": {
			"username": "oliverjam",
			"email": "oliverjamesphillips@gmail.com"
		},
		"maintainers": [
			{
				"username": "oliverjam",
				"email": "oliverjamesphillips@gmail.com"
			}
		]
	},
	"score": {
		"final": 0.19664267212365927,
		"detail": {
			"quality": 0.5288367301487213,
			"popularity": 0.018805882688673784,
			"maintenance": 0.089741697537163
		}
	},
	"searchScore": 1.540346e-8
}