{
	"package": {
		"name": "@panta/svelte-router",
		"scope": "panta",
		"version": "1.0.5",
		"description": "Svelte router based on alshdavid/crayon",
		"keywords": [
			"svelte"
		],
		"date": "2019-10-08T12:25:06.350Z",
		"links": {
			"npm": "https://www.npmjs.com/package/%40panta%2Fsvelte-router",
			"homepage": "https://github.com/panta/svelte-router#readme",
			"repository": "https://github.com/panta/svelte-router",
			"bugs": "https://github.com/panta/svelte-router/issues"
		},
		"author": {
			"name": "Marco Pantaleoni",
			"email": "marco.pantaleoni@gmail.com"
		},
		"publisher": {
			"username": "panta",
			"email": "marco.pantaleoni+npm@gmail.com"
		},
		"maintainers": [
			{
				"username": "panta",
				"email": "marco.pantaleoni+npm@gmail.com"
			}
		]
	},
	"score": {
		"final": 0.1892841133178606,
		"detail": {
			"quality": 0.504347428847757,
			"popularity": 0.018772258644361335,
			"maintenance": 0.089741697537163
		}
	},
	"searchScore": 1.0349839e-8
}