{
	"package": {
		"name": "@pixss/svelte",
		"scope": "pixss",
		"version": "1.2.2",
		"description": "The Svelte UI component based on Pixss Css",
		"keywords": [
			"svelte",
			"component",
			"library"
		],
		"date": "2021-02-13T03:25:51.141Z",
		"links": {
			"npm": "https://www.npmjs.com/package/%40pixss%2Fsvelte",
			"homepage": "https://github.com/vikbert/pixssvelte#readme",
			"repository": "https://github.com/vikbert/pixssvelte",
			"bugs": "https://github.com/vikbert/pixssvelte/issues"
		},
		"author": {
			"name": "segentor"
		},
		"publisher": {
			"username": "segentor",
			"email": "segentor@gmail.com"
		},
		"maintainers": [
			{
				"username": "segentor",
				"email": "segentor@gmail.com"
			}
		]
	},
	"score": {
		"final": 0.19982859394164731,
		"detail": {
			"quality": 0.5395361922957908,
			"popularity": 0.018737548899722945,
			"maintenance": 0.089741697537163
		}
	},
	"searchScore": 2.2514666e-8
}