{
	"package": {
		"name": "@quentincaffeino/manypixels-svelte",
		"scope": "quentincaffeino",
		"version": "0.2.2",
		"description": "Manypixels SVG Illustrations for svelte",
		"keywords": [
			"front-end",
			"manypixels",
			"illustrations",
			"svg",
			"svelte"
		],
		"date": "2021-07-26T14:51:50.167Z",
		"links": {
			"npm": "https://www.npmjs.com/package/%40quentincaffeino%2Fmanypixels-svelte",
			"homepage": "https://github.com/quentincaffeino/manypixels-illustrations#readme",
			"repository": "https://github.com/quentincaffeino/manypixels-illustrations",
			"bugs": "https://github.com/quentincaffeino/manypixels-illustrations/issues"
		},
		"author": {
			"name": "quentincaffeino",
			"email": "sergey95zu@gmail.com",
			"username": "quentincaffeino"
		},
		"publisher": {
			"username": "quentincaffeino",
			"email": "sergey95zu@gmail.com"
		},
		"maintainers": [
			{
				"username": "quentincaffeino",
				"email": "sergey95zu@gmail.com"
			}
		]
	},
	"flags": {
		"unstable": true
	},
	"score": {
		"final": 0.18715390026452922,
		"detail": {
			"quality": 0.4228837357107883,
			"popularity": 0.0015288687180486996,
			"maintenance": 0.1707247871427877
		}
	},
	"searchScore": 6.127125e-9
}