{
	"package": {
		"name": "@rutynka/helper-progress",
		"scope": "rutynka",
		"version": "0.1.3",
		"description": "Svelte super simple heatmap calendar based on Local Storage",
		"keywords": [
			"svelte",
			"progress",
			"calendar",
			"local storage",
			"heatmap",
			"helper",
			"quiz",
			"rutynka"
		],
		"date": "2022-02-11T21:42:24.056Z",
		"links": {
			"npm": "https://www.npmjs.com/package/%40rutynka%2Fhelper-progress",
			"homepage": "https://github.com/rutynka/helper-progress-calendar",
			"repository": "https://github.com/rutynka/helper-progress-calendar",
			"bugs": "https://github.com/rutynka/helper-progress-calendar/issues"
		},
		"author": {
			"name": "ru7ynk4"
		},
		"publisher": {
			"username": "all-the-fish",
			"email": "rutynka@protonmail.com"
		},
		"maintainers": [
			{
				"username": "all-the-fish",
				"email": "rutynka@protonmail.com"
			}
		]
	},
	"flags": {
		"unstable": true
	},
	"score": {
		"final": 0.22194826162374523,
		"detail": {
			"quality": 0.39802258930009876,
			"popularity": 0.027436072263054556,
			"maintenance": 0.26553959869041865
		}
	},
	"searchScore": 2.7857466e-8
}