{
	"package": {
		"name": "@svonic/ui",
		"scope": "svonic",
		"version": "1.0.0-next.35",
		"description": "Testing",
		"keywords": [
			"svelte",
			"sveltekit",
			"ionic"
		],
		"date": "2022-12-26T06:31:41.593Z",
		"links": {
			"npm": "https://www.npmjs.com/package/%40svonic%2Fui"
		},
		"author": {
			"name": "Robert"
		},
		"publisher": {
			"username": "daimyo",
			"email": "robusa8818@gmail.com"
		},
		"maintainers": [
			{
				"username": "daimyo",
				"email": "robusa8818@gmail.com"
			}
		]
	},
	"flags": {
		"unstable": true
	},
	"score": {
		"final": 0.2006888401097305,
		"detail": {
			"quality": 0.2789709984822165,
			"popularity": 0.0027229885583892168,
			"maintenance": 0.33155569877036956
		}
	},
	"searchScore": 5.5454836e-9
}