{
	"package": {
		"name": "apollo-server3-sveltekit",
		"scope": "unscoped",
		"version": "0.9.5",
		"description": "The Ultimate Integration of Apollo Server 3 for Your SvelteKit App",
		"keywords": [
			"GraphQL",
			"Apollo",
			"Svelte",
			"SvelteKit",
			"Svelte",
			"Apollo Server",
			"Apollo Server 3",
			"Apollo Server 3 SvelteKit",
			"Server",
			"Javascript"
		],
		"date": "2022-12-27T21:53:06.106Z",
		"links": {
			"npm": "https://www.npmjs.com/package/apollo-server3-sveltekit",
			"homepage": "https://github.com/jjjjose/apollo-server3-sveltekit#readme",
			"repository": "https://github.com/jjjjose/apollo-server3-sveltekit",
			"bugs": "https://github.com/jjjjose/apollo-server3-sveltekit/issues"
		},
		"author": {
			"name": "jjjjose"
		},
		"publisher": {
			"username": "jjjjose",
			"email": "jjjjoseignacio@gmail.com"
		},
		"maintainers": [
			{
				"username": "jjjjose",
				"email": "jjjjoseignacio@gmail.com"
			}
		]
	},
	"flags": {
		"unstable": true
	},
	"score": {
		"final": 0.2213044345746062,
		"detail": {
			"quality": 0.3422980387182727,
			"popularity": 0.005566732264164973,
			"maintenance": 0.3333333333333333
		}
	},
	"searchScore": 3.19132e-8
}