{
	"package": {
		"name": "bridge-svelte-notification",
		"scope": "unscoped",
		"version": "1.1.0",
		"description": "A notification component for sveltejs",
		"keywords": [
			"svelte",
			"notification",
			"alert"
		],
		"date": "2020-04-17T20:08:35.594Z",
		"links": {
			"npm": "https://www.npmjs.com/package/bridge-svelte-notification",
			"homepage": "https://github.com/bitfumes/bridge-svelte-notification#readme",
			"repository": "https://github.com/bitfumes/bridge-svelte-notification"
		},
		"author": {
			"name": "sarthaksavvy"
		},
		"publisher": {
			"username": "bitfumes",
			"email": "bitfumes@gmail.com"
		},
		"maintainers": [
			{
				"username": "bitfumes",
				"email": "bitfumes@gmail.com"
			}
		]
	},
	"score": {
		"final": 0.1847569091390714,
		"detail": {
			"quality": 0.5097513359337762,
			"popularity": 0.0012054692026613517,
			"maintenance": 0.089741697537163
		}
	},
	"searchScore": 5.495533e-9
}