{
	"package": {
		"name": "chasi-lib",
		"scope": "unscoped",
		"version": "0.0.31",
		"description": "Everything you need to build a Svelte project, powered by [`create-svelte`](https://github.com/sveltejs/kit/tree/master/packages/create-svelte);",
		"date": "2022-10-07T13:01:54.694Z",
		"links": {
			"npm": "https://www.npmjs.com/package/chasi-lib"
		},
		"publisher": {
			"username": "chazy",
			"email": "luismanuelchazy@gmail.com"
		},
		"maintainers": [
			{
				"username": "chazy",
				"email": "luismanuelchazy@gmail.com"
			}
		]
	},
	"flags": {
		"unstable": true
	},
	"score": {
		"final": 0.22105243967799731,
		"detail": {
			"quality": 0.3263276266855747,
			"popularity": 0.018535671444737813,
			"maintenance": 0.3333333333333333
		}
	},
	"searchScore": 1.1451519e-8
}