{
	"package": {
		"name": "graphql-crud-sveltekit",
		"scope": "unscoped",
		"version": "0.0.9",
		"description": "fonction crud utilisant graphql, créer un client graphql et vous fournis des fonctions crud déja préparées, package utiliser pour graphcms",
		"keywords": [
			"crud",
			"graphcms",
			"sveltekit",
			"woopear",
			"graphql"
		],
		"date": "2022-01-26T09:02:55.823Z",
		"links": {
			"npm": "https://www.npmjs.com/package/graphql-crud-sveltekit"
		},
		"author": {
			"name": "woopear",
			"email": "woopears@gmail.com",
			"username": "woopear"
		},
		"publisher": {
			"username": "woopear",
			"email": "woopears@gmail.com"
		},
		"maintainers": [
			{
				"username": "woopear",
				"email": "woopears@gmail.com"
			}
		]
	},
	"flags": {
		"unstable": true
	},
	"score": {
		"final": 0.20339855567446213,
		"detail": {
			"quality": 0.3792891023433832,
			"popularity": 0.02377499409324937,
			"maintenance": 0.23225879153945686
		}
	},
	"searchScore": 8.526066e-9
}