{
	"package": {
		"name": "integral-svelte",
		"scope": "unscoped",
		"version": "0.0.7",
		"description": "![Integral banner](/static/cover.svg)",
		"keywords": [
			"svelte",
			"accessibility",
			"a11y",
			"components",
			"keyboard",
			"sveltekit",
			"typescript"
		],
		"date": "2021-07-10T20:41:49.820Z",
		"links": {
			"npm": "https://www.npmjs.com/package/integral-svelte",
			"homepage": "https://github.com/didier/integral",
			"repository": "https://github.com/didier/integral",
			"bugs": "https://github.com/didier/integral/issues"
		},
		"author": {
			"name": "Didier Catz",
			"email": "info@didiercatz.com",
			"url": "https://didiercatz.com",
			"username": "didiercatz"
		},
		"publisher": {
			"username": "didiercatz",
			"email": "info@didiercatz.com"
		},
		"maintainers": [
			{
				"username": "didiercatz",
				"email": "info@didiercatz.com"
			}
		]
	},
	"flags": {
		"unstable": true
	},
	"score": {
		"final": 0.1955133965374008,
		"detail": {
			"quality": 0.40415024875407274,
			"popularity": 0.0017865519597952627,
			"maintenance": 0.2104086535007161
		}
	},
	"searchScore": 1.0515582e-8
}