{
	"package": {
		"name": "iohpeditcomp",
		"scope": "unscoped",
		"version": "2.0.1",
		"description": "svelte components with bulma css for form edits",
		"date": "2023-01-23T19:26:18.282Z",
		"links": {
			"npm": "https://www.npmjs.com/package/iohpeditcomp"
		},
		"publisher": {
			"username": "iohpgti",
			"email": "gti@ldcc.do"
		},
		"maintainers": [
			{
				"username": "iohpgti",
				"email": "gti@ldcc.do"
			}
		]
	},
	"score": {
		"final": 0.24045905391370426,
		"detail": {
			"quality": 0.39883549845339944,
			"popularity": 0.011833536317193683,
			"maintenance": 0.3333333333333333
		}
	},
	"searchScore": 3.254937e-8
}