{
	"package": {
		"name": "oaf-svelte-routing",
		"scope": "unscoped",
		"version": "2.0.0",
		"description": "An accessible wrapper for [Svelte Routing](https://github.com/EmilTholin/svelte-routing).",
		"date": "2020-01-30T11:39:57.392Z",
		"links": {
			"npm": "https://www.npmjs.com/package/oaf-svelte-routing",
			"homepage": "https://github.com/oaf-project/oaf-svelte-routing#readme",
			"repository": "https://github.com/oaf-project/oaf-svelte-routing",
			"bugs": "https://github.com/oaf-project/oaf-svelte-routing/issues"
		},
		"publisher": {
			"username": "danielnixon",
			"email": "dan.nixon@gmail.com"
		},
		"maintainers": [
			{
				"username": "danielnixon",
				"email": "dan.nixon@gmail.com"
			}
		]
	},
	"score": {
		"final": 0.3254986455020867,
		"detail": {
			"quality": 0.9783781290196104,
			"popularity": 0.0016446075948473565,
			"maintenance": 0.089741697537163
		}
	},
	"searchScore": 0.000010649627
}