{
	"package": {
		"name": "svelte-kit-app",
		"scope": "unscoped",
		"version": "0.0.1",
		"description": "Everything you need to build a Svelte project, powered by [`create-svelte`](https://github.com/sveltejs/kit/tree/master/packages/create-svelte).",
		"date": "2022-08-07T11:47:33.181Z",
		"links": {
			"npm": "https://www.npmjs.com/package/svelte-kit-app"
		},
		"publisher": {
			"username": "codemunha",
			"email": "codemunha@gmail.com"
		},
		"maintainers": [
			{
				"username": "codemunha",
				"email": "codemunha@gmail.com"
			}
		]
	},
	"flags": {
		"unstable": true
	},
	"score": {
		"final": 0.18622008332269444,
		"detail": {
			"quality": 0.34835864020984353,
			"popularity": 0.0012054692026613517,
			"maintenance": 0.23225879153945686
		}
	},
	"searchScore": 4.5331086e-9
}