{
	"package": {
		"name": "svelte-audio-player",
		"scope": "unscoped",
		"version": "0.0.1",
		"description": "Component that wraps html audio tag for building custom audio player.",
		"date": "2022-03-20T12:41:33.506Z",
		"links": {
			"npm": "https://www.npmjs.com/package/svelte-audio-player"
		},
		"publisher": {
			"username": "dandiws",
			"email": "dandiwiratsangka@gmail.com"
		},
		"maintainers": [
			{
				"username": "dandiws",
				"email": "dandiwiratsangka@gmail.com"
			}
		]
	},
	"flags": {
		"unstable": true
	},
	"score": {
		"final": 0.18760637241465544,
		"detail": {
			"quality": 0.35118877309626423,
			"popularity": 0.0027404669913322307,
			"maintenance": 0.23225879153945686
		}
	},
	"searchScore": 4.2940886e-9
}