{
	"package": {
		"name": "svelte-pwa",
		"scope": "unscoped",
		"version": "1.0.2",
		"description": "A command line to create a svelte progressive web app starter",
		"keywords": [
			"oclif"
		],
		"date": "2020-05-31T00:21:38.181Z",
		"links": {
			"npm": "https://www.npmjs.com/package/svelte-pwa"
		},
		"author": {
			"name": "Jenaro @jenaro94"
		},
		"publisher": {
			"username": "cjenaro",
			"email": "jen.calvineo@gmail.com"
		},
		"maintainers": [
			{
				"username": "cjenaro",
				"email": "jen.calvineo@gmail.com"
			}
		]
	},
	"score": {
		"final": 0.19930924233625624,
		"detail": {
			"quality": 0.557397073296747,
			"popularity": 0.0019443605977859507,
			"maintenance": 0.089741697537163
		}
	},
	"searchScore": 1.4948066e-8
}