{
	"package": {
		"name": "svelte-resize-observer-action",
		"scope": "unscoped",
		"version": "0.0.2",
		"description": "Svelte use:action for element resize notifications using ResizeObserver.",
		"keywords": [
			"svelte",
			"use",
			"action",
			"resize",
			"resizeobserver"
		],
		"date": "2023-01-04T19:18:24.890Z",
		"links": {
			"npm": "https://www.npmjs.com/package/svelte-resize-observer-action",
			"homepage": "https://captaincodeman.github.io/svelte-resize-observer-action/",
			"repository": "https://github.com/captaincodeman/svelte-resize-observer-action",
			"bugs": "https://github.com/captaincodeman/svelte-resize-observer-action/issues"
		},
		"author": {
			"name": "Simon Green",
			"email": "simon@captaincodeman.com",
			"url": "https://www.captaincodeman.com/",
			"username": "captaincodeman"
		},
		"publisher": {
			"username": "captaincodeman",
			"email": "simon@captaincodeman.com"
		},
		"maintainers": [
			{
				"username": "captaincodeman",
				"email": "simon@captaincodeman.com"
			}
		]
	},
	"flags": {
		"unstable": true
	},
	"score": {
		"final": 0.25760492279392555,
		"detail": {
			"quality": 0.43476815925336065,
			"popularity": 0.030374121915592106,
			"maintenance": 0.3329815209927432
		}
	},
	"searchScore": 4.9475284e-7
}