{
	"package": {
		"name": "sveltemeacoffee",
		"scope": "unscoped",
		"version": "0.0.1",
		"description": "Fully Configurable Buy Me A Coffee button in svelte",
		"keywords": [
			"svelte",
			"buymeacoffee",
			"coffee",
			"buy me a coffee"
		],
		"date": "2022-06-25T20:53:52.345Z",
		"links": {
			"npm": "https://www.npmjs.com/package/sveltemeacoffee"
		},
		"author": {
			"name": "Samuel C Tyler",
			"email": "@skamansam",
			"url": "https://rudeboy.dev"
		},
		"publisher": {
			"username": "skamansam",
			"email": "skamansam@gmail.com"
		},
		"maintainers": [
			{
				"username": "skamansam",
				"email": "skamansam@gmail.com"
			}
		]
	},
	"flags": {
		"unstable": true
	},
	"score": {
		"final": 0.1796970033772159,
		"detail": {
			"quality": 0.3263276266855747,
			"popularity": 0.0014518238078102884,
			"maintenance": 0.23225879153945686
		}
	},
	"searchScore": 2.2123476e-9
}