{
	"package": {
		"name": "svg-to-svelte",
		"scope": "unscoped",
		"version": "2.2.1",
		"description": "Convert SVG files to Svelte components",
		"keywords": [
			"svelte",
			"svelte component",
			"svg",
			"icon",
			"library"
		],
		"date": "2021-07-24T13:55:06.529Z",
		"links": {
			"npm": "https://www.npmjs.com/package/svg-to-svelte"
		},
		"author": {
			"name": "Eric Liu",
			"url": "https://github.com/metonym"
		},
		"publisher": {
			"username": "metonym",
			"email": "ericyl.us@gmail.com"
		},
		"maintainers": [
			{
				"username": "metonym",
				"email": "ericyl.us@gmail.com"
			}
		]
	},
	"score": {
		"final": 0.2246380957280324,
		"detail": {
			"quality": 0.6191815227934985,
			"popularity": 0.004091318510533315,
			"maintenance": 0.10700479260370344
		}
	},
	"searchScore": 8.951099e-8
}