{
	"package": {
		"name": "tui-editor-svelte",
		"scope": "unscoped",
		"version": "0.0.1",
		"keywords": [
			"svelte",
			"component",
			"library",
			"tui",
			"editor"
		],
		"date": "2021-04-09T05:55:24.562Z",
		"links": {
			"npm": "https://www.npmjs.com/package/tui-editor-svelte",
			"homepage": "https://ui.toast.com",
			"repository": "https://github.com/composite/tui-editor-svelte",
			"bugs": "https://github.com/composite/tui-editor-svelte/issues"
		},
		"author": {
			"name": "Composite",
			"email": "ukjinplant@msn.com",
			"username": "ukjinplant"
		},
		"publisher": {
			"username": "ukjinplant",
			"email": "ukjinplant@msn.com"
		},
		"maintainers": [
			{
				"username": "ukjinplant",
				"email": "ukjinplant@msn.com"
			}
		]
	},
	"flags": {
		"unstable": true
	},
	"score": {
		"final": 0.19996226188539212,
		"detail": {
			"quality": 0.4324582543775872,
			"popularity": 0.0025576545827927736,
			"maintenance": 0.19808458990896707
		}
	},
	"searchScore": 1.3685325e-8
}